almanach/__init__.py
almanach/api/__init__.py
almanach/api/auth_adapter.py
almanach/api/main.py
almanach/api/auth/__init__.py
almanach/api/auth/base_auth.py
almanach/api/auth/keystone_auth.py
almanach/api/auth/mixed_auth.py
almanach/api/auth/private_key_auth.py
almanach/api/v1/__init__.py
almanach/api/v1/routes.py
almanach/collector/__init__.py
almanach/collector/main.py
almanach/collector/messaging.py
almanach/collector/notification.py
almanach/collector/service.py
almanach/collector/filters/__init__.py
almanach/collector/filters/base_filter.py
almanach/collector/filters/delete_instance_before_completion_filter.py
almanach/collector/filters/errored_instance_filter.py
almanach/collector/handlers/__init__.py
almanach/collector/handlers/base_handler.py
almanach/collector/handlers/instance_handler.py
almanach/collector/handlers/volume_handler.py
almanach/collector/handlers/volume_type_handler.py
almanach/core/__init__.py
almanach/core/exception.py
almanach/core/factory.py
almanach/core/model.py
almanach/core/opts.py
almanach/core/controllers/__init__.py
almanach/core/controllers/application_controller.py
almanach/core/controllers/base_controller.py
almanach/core/controllers/entity_controller.py
almanach/core/controllers/instance_controller.py
almanach/core/controllers/volume_controller.py
almanach/core/controllers/volume_type_controller.py
almanach/core/helpers/__init__.py
almanach/core/helpers/date_helper.py
almanach/hacking/__init__.py
almanach/hacking/checks.py
almanach/storage/__init__.py
almanach/storage/storage_driver.py
almanach/storage/drivers/__init__.py
almanach/storage/drivers/base_driver.py
almanach/storage/drivers/mongodb_driver.py
almanach/tests/__init__.py
almanach/tests/tempest/README.rst
almanach/tests/tempest/__init__.py
almanach/tests/tempest/clients.py
almanach/tests/tempest/config.py
almanach/tests/tempest/plugin.py
almanach/tests/tempest/services/__init__.py
almanach-4.1.0.dist-info/DESCRIPTION.rst
almanach-4.1.0.dist-info/METADATA
almanach-4.1.0.dist-info/RECORD
almanach-4.1.0.dist-info/WHEEL
almanach-4.1.0.dist-info/entry_points.txt
almanach-4.1.0.dist-info/metadata.json
almanach-4.1.0.dist-info/pbr.json
almanach-4.1.0.dist-info/top_level.txt
