Metadata-Version: 2.0
Name: almanach
Version: 4.1.0
Summary: Stores usage of OpenStack volumes and instances for each tenant
Home-page: https://almanach.readthedocs.io/
Author: Internap Hosting
Author-email: opensource@internap.com
License: Apache-2
Platform: UNKNOWN
Classifier: Development Status :: 5 - Production/Stable
Classifier: Intended Audience :: Developers
Classifier: Intended Audience :: Information Technology
Classifier: Intended Audience :: System Administrators
Classifier: Intended Audience :: Telecommunications Industry
Classifier: License :: OSI Approved :: Apache Software License
Classifier: Operating System :: POSIX
Classifier: Programming Language :: Python :: 2.7
Classifier: Programming Language :: Python :: 3.4
Classifier: Programming Language :: Python :: 3.5
Requires-Dist: Flask (>=0.10,<1.0,!=0.11)
Requires-Dist: jsonpickle (==0.7.1)
Requires-Dist: keystoneauth1 (>=2.14.0)
Requires-Dist: kombu (>=4.0.0,!=4.0.2)
Requires-Dist: oslo.config (>=3.14.0)
Requires-Dist: oslo.log (>=3.11.0)
Requires-Dist: oslo.messaging (>=5.14.0)
Requires-Dist: oslo.serialization (>=1.10.0)
Requires-Dist: oslo.service (>=1.10.0)
Requires-Dist: pbr (>=1.8)
Requires-Dist: pymongo (!=3.1,>=3.0.2)
Requires-Dist: python-keystoneclient (>=3.8.0)
Requires-Dist: pytz (>=2013.6)
Requires-Dist: six (>=1.9.0)
Requires-Dist: voluptuous (>=0.8.9)
